README.txt
setup.cfg
setup.py
SonyAPI/__init__.py
SonyAPI/api_const.py
SonyAPI/application.py
SonyAPI/browser.py
SonyAPI/channel.py
SonyAPI/event.py
SonyAPI/exception.py
SonyAPI/inputs.py
SonyAPI/logger.py
SonyAPI/media.py
SonyAPI/recording.py
SonyAPI/speaker.py
SonyAPI/test.py
SonyAPI/utils.py
SonyAPI/version.py
SonyAPI/volume.py
SonyAPI.egg-info/PKG-INFO
SonyAPI.egg-info/SOURCES.txt
SonyAPI.egg-info/dependency_links.txt
SonyAPI.egg-info/requires.txt
SonyAPI.egg-info/top_level.txt
SonyAPI.egg-info/zip-safe