Metadata-Version: 1.1
Name: SonyAPI
Version: 0.1.1b1
Summary: Sony Bravia TV interface (generation 3)
Home-page: https://github.com/kdschlosser/SonyAPI
Author: Kevin G. Schlosser
Author-email: Kevin.G.Schlosser@gmail.com
License: GPL-2.0
Download-URL: https://github.com/kdschlosser/SonyAPI/archive/0.1.1b1.tar.gz
Keywords: Sony SonyAPI Bravia BraviaAPI SonyTV BravieTV
Platform: UNKNOWN
Classifier: Development Status :: 5 - Production/Stable
Classifier: Operating System :: MacOS
Classifier: Operating System :: Microsoft :: Windows
Classifier: Operating System :: Unix
Classifier: Intended Audience :: Developers
Classifier: Intended Audience :: End Users/Desktop
Classifier: Intended Audience :: Other Audience
Classifier: License :: OSI Approved :: GNU General Public License v2 (GPLv2)
Classifier: Natural Language :: English
Classifier: Programming Language :: Python
Classifier: Topic :: Multimedia
Classifier: Topic :: Other/Nonlisted Topic
Classifier: Topic :: Home Automation
